django_models_redis_cache/__init__.py
django_models_redis_cache/cache.py
django_models_redis_cache/core.py
django_models_redis_cache/models.py
django_models_redis_cache/utils.py
django_models_redis_cache-4.4.3.dist-info/LICENSE
django_models_redis_cache-4.4.3.dist-info/WHEEL
django_models_redis_cache-4.4.3.dist-info/METADATA
django_models_redis_cache-4.4.3.dist-info/RECORD
