Metadata-Version: 2.1
Name: django-models-redis-cache
Version: 4.4.3
Summary: Django Models Redis Cache (DMoReCa), library that gives your specified Django models regular caching via Redis
Home-page: https://github.com/gh0st-work/django_models_redis_cache
License: MIT
Keywords: python,redis,ORM,django,database
Author: Anton Nechaev
Author-email: antonnechaev990@gmail.com
Requires-Python: >=3.6,<4.0
Classifier: Development Status :: 2 - Pre-Alpha
Classifier: Environment :: Web Environment
Classifier: Framework :: Django
Classifier: Framework :: Django :: 3.0
Classifier: Intended Audience :: Developers
Classifier: License :: OSI Approved :: MIT License
Classifier: Operating System :: OS Independent
Classifier: Programming Language :: Python
Classifier: Programming Language :: Python :: 3
Classifier: Programming Language :: Python :: 3 :: Only
Classifier: Programming Language :: Python :: 3.6
Classifier: Programming Language :: Python :: 3.7
Classifier: Programming Language :: Python :: 3.8
Classifier: Programming Language :: Python :: 3.9
Classifier: Topic :: Database :: Front-Ends
Classifier: Topic :: Internet
Classifier: Topic :: Internet :: WWW/HTTP
Classifier: Topic :: Internet :: WWW/HTTP :: Dynamic Content
Classifier: Topic :: Internet :: WWW/HTTP :: HTTP Servers
Classifier: Topic :: Internet :: WWW/HTTP :: Site Management
Classifier: Topic :: Software Development
Classifier: Topic :: Software Development :: Libraries
Classifier: Topic :: Software Development :: Libraries :: Python Modules
Classifier: Topic :: Software Development :: Object Brokering
Classifier: Topic :: Utilities
Requires-Dist: Django (>=3.0,<4.0)
Requires-Dist: redis (>=3.5.3,<4.0.0)
Project-URL: Repository, https://github.com/gh0st-work/django_models_redis_cache
